client_bank_exchange_1c/__init__.py
client_bank_exchange_1c/client_bank_exchange_1c.py
client_bank_exchange_1c/django_client_bank_exchange_1c.py
client_bank_exchange_1c_py2-0.2.4.dist-info/METADATA
client_bank_exchange_1c_py2-0.2.4.dist-info/WHEEL
client_bank_exchange_1c_py2-0.2.4.dist-info/top_level.txt
client_bank_exchange_1c_py2-0.2.4.dist-info/RECORD
